django_admin_client/__init__.py
django_admin_client/base.py
django_admin_client/exceptions.py
django_admin_client/helpers.py
django_admin_client/settings.py
django_admin_client/templates.py
django_admin_client-0.2.4.dist-info/LICENSE
django_admin_client-0.2.4.dist-info/METADATA
django_admin_client-0.2.4.dist-info/WHEEL
django_admin_client-0.2.4.dist-info/entry_points.txt
django_admin_client-0.2.4.dist-info/top_level.txt
django_admin_client-0.2.4.dist-info/RECORD
