Metadata-Version: 2.1
Name: django-admin-client
Version: 0.2.4
Summary: Django admin client
Home-page: https://gitlab.com/y3g0r/django-admin-client
Author: Yegor Ivashchenko
Author-email: yegor.ivashchenko@protonmail.com
License: MIT
Platform: UNKNOWN
Requires-Dist: requests
Requires-Dist: BeautifulSoup4
Requires-Dist: python-dotenv
